{
    "os": "Linux-3.10.0-1160.76.1.el7.x86_64-x86_64-with-glibc2.17",
    "python": "3.8.13",
    "heartbeatAt": "2023-09-02T15:40:17.371365",
    "startedAt": "2023-09-02T15:40:15.873940",
    "docker": null,
    "cuda": null,
    "args": [],
    "state": "running",
    "program": "lstm_testing.py",
    "codePath": "LIM/neural_networks/lstm_testing.py",
    "git": {
        "remote": "https://github.com/Felix6464/ML_Climate_Science_Research_Project.git",
        "commit": "8a2923b331b1ea5b5ecc8fa84291578f45cf1e23"
    },
    "email": "felix.boette@student.uni-tuebingen.de",
    "root": "/mnt/qb/home/goswami/gkd235/ML_Climate_Science_Research_Project",
    "host": "slurm-bm-20.novalocal",
    "username": "gkd235",
    "executable": "/mnt/qb/work/goswami/gkd235/path/to/conda/envs/felix_c/bin/python3",
    "cpu_count": 36,
    "cpu_count_logical": 72,
    "cpu_freq": {
        "current": 3269.633166666666,
        "min": 1000.0,
        "max": 3900.0
    },
    "cpu_freq_per_core": [
        {
            "current": 2992.443,
            "min": 1000.0,
            "max": 3900.0
        },
        {
            "current": 2938.964,
            "min": 1000.0,
            "max": 3900.0
        },
        {
            "current": 3300.146,
            "min": 1000.0,
            "max": 3900.0
        },
        {
            "current": 3299.829,
            "min": 1000.0,
            "max": 3900.0
        },
        {
            "current": 3300.146,
            "min": 1000.0,
            "max": 3900.0
        },
        {
            "current": 3081.787,
            "min": 1000.0,
            "max": 3900.0
        },
        {
            "current": 3300.146,
            "min": 1000.0,
            "max": 3900.0
        },
        {
            "current": 3199.06,
            "min": 1000.0,
            "max": 3900.0
        },
        {
            "current": 3299.987,
            "min": 1000.0,
            "max": 3900.0
        },
        {
            "current": 3299.987,
            "min": 1000.0,
            "max": 3900.0
        },
        {
            "current": 3299.829,
            "min": 1000.0,
            "max": 3900.0
        },
        {
            "current": 3299.829,
            "min": 1000.0,
            "max": 3900.0
        },
        {
            "current": 3299.987,
            "min": 1000.0,
            "max": 3900.0
        },
        {
            "current": 3299.829,
            "min": 1000.0,
            "max": 3900.0
        },
        {
            "current": 3299.987,
            "min": 1000.0,
            "max": 3900.0
        },
        {
            "current": 3291.259,
            "min": 1000.0,
            "max": 3900.0
        },
        {
            "current": 3299.829,
            "min": 1000.0,
            "max": 3900.0
        },
        {
            "current": 3299.829,
            "min": 1000.0,
            "max": 3900.0
        },
        {
            "current": 3325.537,
            "min": 1000.0,
            "max": 3900.0
        },
        {
            "current": 3299.987,
            "min": 1000.0,
            "max": 3900.0
        },
        {
            "current": 3346.166,
            "min": 1000.0,
            "max": 3900.0
        },
        {
            "current": 3299.67,
            "min": 1000.0,
            "max": 3900.0
        },
        {
            "current": 3321.252,
            "min": 1000.0,
            "max": 3900.0
        },
        {
            "current": 3299.829,
            "min": 1000.0,
            "max": 3900.0
        },
        {
            "current": 3336.169,
            "min": 1000.0,
            "max": 3900.0
        },
        {
            "current": 3332.36,
            "min": 1000.0,
            "max": 3900.0
        },
        {
            "current": 3299.829,
            "min": 1000.0,
            "max": 3900.0
        },
        {
            "current": 3264.758,
            "min": 1000.0,
            "max": 3900.0
        },
        {
            "current": 3312.365,
            "min": 1000.0,
            "max": 3900.0
        },
        {
            "current": 3311.889,
            "min": 1000.0,
            "max": 3900.0
        },
        {
            "current": 3337.28,
            "min": 1000.0,
            "max": 3900.0
        },
        {
            "current": 3309.033,
            "min": 1000.0,
            "max": 3900.0
        },
        {
            "current": 3073.535,
            "min": 1000.0,
            "max": 3900.0
        },
        {
            "current": 3326.171,
            "min": 1000.0,
            "max": 3900.0
        },
        {
            "current": 3299.987,
            "min": 1000.0,
            "max": 3900.0
        },
        {
            "current": 3335.693,
            "min": 1000.0,
            "max": 3900.0
        },
        {
            "current": 2746.948,
            "min": 1000.0,
            "max": 3900.0
        },
        {
            "current": 3105.59,
            "min": 1000.0,
            "max": 3900.0
        },
        {
            "current": 3299.987,
            "min": 1000.0,
            "max": 3900.0
        },
        {
            "current": 3299.353,
            "min": 1000.0,
            "max": 3900.0
        },
        {
            "current": 3283.483,
            "min": 1000.0,
            "max": 3900.0
        },
        {
            "current": 3202.392,
            "min": 1000.0,
            "max": 3900.0
        },
        {
            "current": 3299.987,
            "min": 1000.0,
            "max": 3900.0
        },
        {
            "current": 3237.78,
            "min": 1000.0,
            "max": 3900.0
        },
        {
            "current": 3299.829,
            "min": 1000.0,
            "max": 3900.0
        },
        {
            "current": 3299.829,
            "min": 1000.0,
            "max": 3900.0
        },
        {
            "current": 3299.829,
            "min": 1000.0,
            "max": 3900.0
        },
        {
            "current": 3299.67,
            "min": 1000.0,
            "max": 3900.0
        },
        {
            "current": 3299.987,
            "min": 1000.0,
            "max": 3900.0
        },
        {
            "current": 3288.879,
            "min": 1000.0,
            "max": 3900.0
        },
        {
            "current": 3289.672,
            "min": 1000.0,
            "max": 3900.0
        },
        {
            "current": 3288.085,
            "min": 1000.0,
            "max": 3900.0
        },
        {
            "current": 3282.055,
            "min": 1000.0,
            "max": 3900.0
        },
        {
            "current": 3293.798,
            "min": 1000.0,
            "max": 3900.0
        },
        {
            "current": 3265.234,
            "min": 1000.0,
            "max": 3900.0
        },
        {
            "current": 3302.526,
            "min": 1000.0,
            "max": 3900.0
        },
        {
            "current": 3332.36,
            "min": 1000.0,
            "max": 3900.0
        },
        {
            "current": 3299.829,
            "min": 1000.0,
            "max": 3900.0
        },
        {
            "current": 3313.317,
            "min": 1000.0,
            "max": 3900.0
        },
        {
            "current": 3309.191,
            "min": 1000.0,
            "max": 3900.0
        },
        {
            "current": 3320.935,
            "min": 1000.0,
            "max": 3900.0
        },
        {
            "current": 3306.494,
            "min": 1000.0,
            "max": 3900.0
        },
        {
            "current": 3300.622,
            "min": 1000.0,
            "max": 3900.0
        },
        {
            "current": 3268.249,
            "min": 1000.0,
            "max": 3900.0
        },
        {
            "current": 3328.393,
            "min": 1000.0,
            "max": 3900.0
        },
        {
            "current": 3317.602,
            "min": 1000.0,
            "max": 3900.0
        },
        {
            "current": 3308.239,
            "min": 1000.0,
            "max": 3900.0
        },
        {
            "current": 3341.247,
            "min": 1000.0,
            "max": 3900.0
        },
        {
            "current": 3318.237,
            "min": 1000.0,
            "max": 3900.0
        },
        {
            "current": 3335.852,
            "min": 1000.0,
            "max": 3900.0
        },
        {
            "current": 3299.511,
            "min": 1000.0,
            "max": 3900.0
        },
        {
            "current": 3299.353,
            "min": 1000.0,
            "max": 3900.0
        }
    ],
    "disk": {
        "total": 1676.225757598877,
        "used": 346.0823554992676
    },
    "gpu": "NVIDIA GeForce RTX 2080 Ti",
    "gpu_count": 1,
    "gpu_devices": [
        {
            "name": "NVIDIA GeForce RTX 2080 Ti",
            "memory_total": 11811160064
        }
    ],
    "memory": {
        "total": 376.36460876464844
    }
}
