{
    "os": "Linux-3.10.0-1160.76.1.el7.x86_64-x86_64-with-glibc2.17",
    "python": "3.8.13",
    "heartbeatAt": "2023-09-05T07:27:48.410510",
    "startedAt": "2023-09-05T07:27:47.515814",
    "docker": null,
    "cuda": null,
    "args": [],
    "state": "running",
    "program": "lstm_training.py",
    "codePath": "LIM/neural_networks/lstm_training.py",
    "git": {
        "remote": "https://github.com/Felix6464/ML_Climate_Science_Research_Project.git",
        "commit": "80ea0d387c8a0512b2666f4dfeb8210756a930e4"
    },
    "email": "felix.boette@student.uni-tuebingen.de",
    "root": "/mnt/qb/home/goswami/gkd235/ML_Climate_Science_Research_Project",
    "host": "slurm-bm-20.novalocal",
    "username": "gkd235",
    "executable": "/mnt/qb/work/goswami/gkd235/path/to/conda/envs/felix_c/bin/python3",
    "cpu_count": 36,
    "cpu_count_logical": 72,
    "cpu_freq": {
        "current": 3368.306138888888,
        "min": 1000.0,
        "max": 3900.0
    },
    "cpu_freq_per_core": [
        {
            "current": 3599.914,
            "min": 1000.0,
            "max": 3900.0
        },
        {
            "current": 3599.914,
            "min": 1000.0,
            "max": 3900.0
        },
        {
            "current": 3453.283,
            "min": 1000.0,
            "max": 3900.0
        },
        {
            "current": 3556.75,
            "min": 1000.0,
            "max": 3900.0
        },
        {
            "current": 3533.422,
            "min": 1000.0,
            "max": 3900.0
        },
        {
            "current": 3506.286,
            "min": 1000.0,
            "max": 3900.0
        },
        {
            "current": 3293.005,
            "min": 1000.0,
            "max": 3900.0
        },
        {
            "current": 3142.883,
            "min": 1000.0,
            "max": 3900.0
        },
        {
            "current": 3233.972,
            "min": 1000.0,
            "max": 3900.0
        },
        {
            "current": 2944.519,
            "min": 1000.0,
            "max": 3900.0
        },
        {
            "current": 3255.395,
            "min": 1000.0,
            "max": 3900.0
        },
        {
            "current": 3258.093,
            "min": 1000.0,
            "max": 3900.0
        },
        {
            "current": 3326.33,
            "min": 1000.0,
            "max": 3900.0
        },
        {
            "current": 2891.357,
            "min": 1000.0,
            "max": 3900.0
        },
        {
            "current": 3217.15,
            "min": 1000.0,
            "max": 3900.0
        },
        {
            "current": 3213.024,
            "min": 1000.0,
            "max": 3900.0
        },
        {
            "current": 3444.714,
            "min": 1000.0,
            "max": 3900.0
        },
        {
            "current": 3542.785,
            "min": 1000.0,
            "max": 3900.0
        },
        {
            "current": 3198.425,
            "min": 1000.0,
            "max": 3900.0
        },
        {
            "current": 3571.032,
            "min": 1000.0,
            "max": 3900.0
        },
        {
            "current": 3406.628,
            "min": 1000.0,
            "max": 3900.0
        },
        {
            "current": 3510.729,
            "min": 1000.0,
            "max": 3900.0
        },
        {
            "current": 3489.465,
            "min": 1000.0,
            "max": 3900.0
        },
        {
            "current": 3300.939,
            "min": 1000.0,
            "max": 3900.0
        },
        {
            "current": 3218.103,
            "min": 1000.0,
            "max": 3900.0
        },
        {
            "current": 3472.485,
            "min": 1000.0,
            "max": 3900.0
        },
        {
            "current": 3269.836,
            "min": 1000.0,
            "max": 3900.0
        },
        {
            "current": 3352.514,
            "min": 1000.0,
            "max": 3900.0
        },
        {
            "current": 3367.431,
            "min": 1000.0,
            "max": 3900.0
        },
        {
            "current": 3343.627,
            "min": 1000.0,
            "max": 3900.0
        },
        {
            "current": 3458.361,
            "min": 1000.0,
            "max": 3900.0
        },
        {
            "current": 3654.028,
            "min": 1000.0,
            "max": 3900.0
        },
        {
            "current": 3176.525,
            "min": 1000.0,
            "max": 3900.0
        },
        {
            "current": 3281.262,
            "min": 1000.0,
            "max": 3900.0
        },
        {
            "current": 3413.452,
            "min": 1000.0,
            "max": 3900.0
        },
        {
            "current": 3424.877,
            "min": 1000.0,
            "max": 3900.0
        },
        {
            "current": 3395.837,
            "min": 1000.0,
            "max": 3900.0
        },
        {
            "current": 3599.914,
            "min": 1000.0,
            "max": 3900.0
        },
        {
            "current": 3257.458,
            "min": 1000.0,
            "max": 3900.0
        },
        {
            "current": 3549.609,
            "min": 1000.0,
            "max": 3900.0
        },
        {
            "current": 3514.855,
            "min": 1000.0,
            "max": 3900.0
        },
        {
            "current": 3574.206,
            "min": 1000.0,
            "max": 3900.0
        },
        {
            "current": 3356.005,
            "min": 1000.0,
            "max": 3900.0
        },
        {
            "current": 3355.212,
            "min": 1000.0,
            "max": 3900.0
        },
        {
            "current": 2920.397,
            "min": 1000.0,
            "max": 3900.0
        },
        {
            "current": 2688.232,
            "min": 1000.0,
            "max": 3900.0
        },
        {
            "current": 3368.066,
            "min": 1000.0,
            "max": 3900.0
        },
        {
            "current": 3272.692,
            "min": 1000.0,
            "max": 3900.0
        },
        {
            "current": 3270.312,
            "min": 1000.0,
            "max": 3900.0
        },
        {
            "current": 3533.422,
            "min": 1000.0,
            "max": 3900.0
        },
        {
            "current": 3383.3,
            "min": 1000.0,
            "max": 3900.0
        },
        {
            "current": 3337.438,
            "min": 1000.0,
            "max": 3900.0
        },
        {
            "current": 3278.247,
            "min": 1000.0,
            "max": 3900.0
        },
        {
            "current": 3529.931,
            "min": 1000.0,
            "max": 3900.0
        },
        {
            "current": 3319.03,
            "min": 1000.0,
            "max": 3900.0
        },
        {
            "current": 3413.134,
            "min": 1000.0,
            "max": 3900.0
        },
        {
            "current": 3463.598,
            "min": 1000.0,
            "max": 3900.0
        },
        {
            "current": 3440.112,
            "min": 1000.0,
            "max": 3900.0
        },
        {
            "current": 3328.71,
            "min": 1000.0,
            "max": 3900.0
        },
        {
            "current": 3338.549,
            "min": 1000.0,
            "max": 3900.0
        },
        {
            "current": 3338.708,
            "min": 1000.0,
            "max": 3900.0
        },
        {
            "current": 3245.874,
            "min": 1000.0,
            "max": 3900.0
        },
        {
            "current": 3582.141,
            "min": 1000.0,
            "max": 3900.0
        },
        {
            "current": 3162.878,
            "min": 1000.0,
            "max": 3900.0
        },
        {
            "current": 3130.029,
            "min": 1000.0,
            "max": 3900.0
        },
        {
            "current": 3297.29,
            "min": 1000.0,
            "max": 3900.0
        },
        {
            "current": 3663.867,
            "min": 1000.0,
            "max": 3900.0
        },
        {
            "current": 3315.539,
            "min": 1000.0,
            "max": 3900.0
        },
        {
            "current": 3395.52,
            "min": 1000.0,
            "max": 3900.0
        },
        {
            "current": 3289.831,
            "min": 1000.0,
            "max": 3900.0
        },
        {
            "current": 3595.947,
            "min": 1000.0,
            "max": 3900.0
        },
        {
            "current": 3502.478,
            "min": 1000.0,
            "max": 3900.0
        }
    ],
    "disk": {
        "total": 1676.225757598877,
        "used": 317.4253959655762
    },
    "gpu": "NVIDIA GeForce RTX 2080 Ti",
    "gpu_count": 1,
    "gpu_devices": [
        {
            "name": "NVIDIA GeForce RTX 2080 Ti",
            "memory_total": 11811160064
        }
    ],
    "memory": {
        "total": 376.36460876464844
    }
}
